odoo/addons/product_packaging_type_required/README.rst
odoo/addons/product_packaging_type_required/__init__.py
odoo/addons/product_packaging_type_required/__manifest__.py
odoo/addons/product_packaging_type_required/data/cron.xml
odoo/addons/product_packaging_type_required/i18n/es.po
odoo/addons/product_packaging_type_required/i18n/it.po
odoo/addons/product_packaging_type_required/i18n/product_packaging_type_required.pot
odoo/addons/product_packaging_type_required/migrations/14.0.1.1.0/post-migrate.py
odoo/addons/product_packaging_type_required/models/__init__.py
odoo/addons/product_packaging_type_required/models/product_packaging_type.py
odoo/addons/product_packaging_type_required/readme/CONTRIBUTORS.rst
odoo/addons/product_packaging_type_required/readme/CREDITS.rst
odoo/addons/product_packaging_type_required/readme/DESCRIPTION.rst
odoo/addons/product_packaging_type_required/readme/USAGE.rst
odoo/addons/product_packaging_type_required/static/description/icon.png
odoo/addons/product_packaging_type_required/static/description/index.html
odoo/addons/product_packaging_type_required/tests/__init__.py
odoo/addons/product_packaging_type_required/tests/test_packaging_required.py
odoo/addons/product_packaging_type_required/views/product_packaging_type_view.xml
odoo14_addon_product_packaging_type_required-14.0.1.1.1.dev6.dist-info/METADATA
odoo14_addon_product_packaging_type_required-14.0.1.1.1.dev6.dist-info/WHEEL
odoo14_addon_product_packaging_type_required-14.0.1.1.1.dev6.dist-info/top_level.txt
odoo14_addon_product_packaging_type_required-14.0.1.1.1.dev6.dist-info/RECORD
